AUTHORS.rst
CONTRIBUTING.rst
HISTORY.rst
LICENSE
MANIFEST.in
README.rst
setup.py
bfab/__init__.py
bfab/bfab.py
bfab.egg-info/PKG-INFO
bfab.egg-info/SOURCES.txt
bfab.egg-info/dependency_links.txt
bfab.egg-info/not-zip-safe
bfab.egg-info/top_level.txt