Metadata-Version: 1.1
Name: bfab
Version: 0.1.0
Summary: Advanced fabric deployments
Home-page: https://github.com/balanced/bfab
Author: Marshall Jones
Author-email: dev@balancedpayments.com
License: BSD
Keywords: bfab
Platform: UNKNOWN
Classifier: Development Status :: 2 - Pre-Alpha
Classifier: Intended Audience :: Developers
Classifier: License :: OSI Approved :: BSD License
Classifier: Natural Language :: English
Classifier: Programming Language :: Python :: 2
Classifier: Programming Language :: Python :: 2.6
Classifier: Programming Language :: Python :: 2.7
Classifier: Programming Language :: Python :: 3
Classifier: Programming Language :: Python :: 3.3
